{
  "plugins": {
    "blink.cmp": {
      "rev": "327fff9",
      "src": "https://github.com/Saghen/blink.cmp",
      "version": ">=0.0.0"
    },
    "conform.nvim": {
      "rev": "cde4da5",
      "src": "https://github.com/stevearc/conform.nvim"
    },
    "everforest": [],
    "friendly-snippets": [],
    "harpoon": {
      "rev": "87b1a35",
      "src": "https://github.com/ThePrimeagen/harpoon",
      "version": "'harpoon2'"
    },
    "nvim-lspconfig": {
      "rev": "2010fc6",
      "src": "https://github.com/neovim/nvim-lspconfig"
    },
    "nvim-treesitter": {
      "rev": "d97d226c",
      "src": "https://github.com/nvim-treesitter/nvim-treesitter",
      "version": "'master'"
    },
    "plenary.nvim": [],
    "telescope-fzf-native.nvim": {
      "rev": "6fea601",
      "src": "https://github.com/nvim-telescope/telescope-fzf-native.nvim"
    },
    "telescope.nvim": [],
    "trouble.nvim": {
      "rev": "bd67efe",
      "src": "https://github.com/folke/trouble.nvim"
    },
    "undotree": [],
    "vim-fugitive": []
  }
}
